sydney_token_extractor/__init__.py
sydney_token_extractor/main.py
sydney_token_extractor-1.0.2.dist-info/licenses/LICENSE
sydney_token_extractor-1.0.2.dist-info/METADATA
sydney_token_extractor-1.0.2.dist-info/WHEEL
sydney_token_extractor-1.0.2.dist-info/entry_points.txt
sydney_token_extractor-1.0.2.dist-info/top_level.txt
sydney_token_extractor-1.0.2.dist-info/RECORD
